via/__init__.py
via/constants.py
via/db.py
via/log.py
via/settings.py
via/utils.py
via/api/__init__.py
via/api/main.py
via/caches/__init__.py
via/caches/bounding_graph_gdfs_cache.py
via/caches/edge_cache.py
via/caches/network_cache.py
via/caches/nxmap_cache.py
via/caches/place_cache.py
via/geojson/__init__.py
via/geojson/generate.py
via/geojson/retrieve.py
via/geojson/utils.py
via/models/__init__.py
via/models/frame.py
via/models/generic.py
via/models/gps.py
via/models/journey.py
via/models/journey_mixins.py
via/models/journeys.py
via/models/point.py
via_api-2.16.0.dist-info/METADATA
via_api-2.16.0.dist-info/WHEEL
via_api-2.16.0.dist-info/entry_points.txt
via_api-2.16.0.dist-info/top_level.txt
via_api-2.16.0.dist-info/RECORD
