Metadata-Version: 2.1
Name: via-api
Version: 2.16.0
Summary: Analysing and serving crowdsourced road quality data
Home-page: https://github.com/RobertLucey/via
Author: Robert Lucey
Requires-Python: >=3.9
Requires-Dist: ujson
Requires-Dist: cached-property
Requires-Dist: packaging
Requires-Dist: reverse-geocoder
Requires-Dist: haversine
Requires-Dist: osmnx
Requires-Dist: requests
Requires-Dist: geopandas
Requires-Dist: python-logging-loki
Requires-Dist: fastapi[all]
Requires-Dist: pydantic
Requires-Dist: pymongo
Requires-Dist: cachetools
Requires-Dist: mappymatch
